catsndogs/__init__.py
catsndogs/data.py
catsndogs/processing.py
catsndogs/pytorch.py
catsndogs/test.py
catsndogs/training.py
catsndogs-0.0.6.dist-info/LICENSE
catsndogs-0.0.6.dist-info/METADATA
catsndogs-0.0.6.dist-info/WHEEL
catsndogs-0.0.6.dist-info/top_level.txt
catsndogs-0.0.6.dist-info/RECORD
