Metadata-Version: 2.1
Name: catsndogs
Version: 0.0.6
Summary: A dataset containing cats and dogs.
Home-page: https://github.com/simonpf/catsndogs
Author: Simon Pfreundschuh
Author-email: simon.pfreundschuh@chalmers.se
License: UNKNOWN
Project-URL: Source, https://github.com/simonpf/catsndogs/
Platform: UNKNOWN
Requires-Python: >=3.6
Requires-Dist: appdirs
Requires-Dist: requests
